CHANGES.rst
MANIFEST.in
README.rst
TODO.rst
setup.cfg
setup.py
Solgema/__init__.py
Solgema.fullcalendar.egg-info/PKG-INFO
Solgema.fullcalendar.egg-info/SOURCES.txt
Solgema.fullcalendar.egg-info/dependency_links.txt
Solgema.fullcalendar.egg-info/entry_points.txt
Solgema.fullcalendar.egg-info/namespace_packages.txt
Solgema.fullcalendar.egg-info/not-zip-safe
Solgema.fullcalendar.egg-info/requires.txt
Solgema.fullcalendar.egg-info/top_level.txt
Solgema/fullcalendar/__init__.py
Solgema/fullcalendar/catalog.py
Solgema/fullcalendar/configure.zcml
Solgema/fullcalendar/content.py
Solgema/fullcalendar/events.py
Solgema/fullcalendar/interfaces.py
Solgema/fullcalendar/options.py
Solgema/fullcalendar/setuphandlers.py
Solgema/fullcalendar/testing.py
Solgema/fullcalendar/utils.py
Solgema/fullcalendar/vocabularies.py
Solgema/fullcalendar/vocabularies.zcml
Solgema/fullcalendar/Extensions/__init__.py
Solgema/fullcalendar/Extensions/install.py
Solgema/fullcalendar/browser/SFAddMenu.pt
Solgema/fullcalendar/browser/__init__.py
Solgema/fullcalendar/browser/actions.py
Solgema/fullcalendar/browser/adapters.py
Solgema/fullcalendar/browser/add_dx_event.pt
Solgema/fullcalendar/browser/collectionquery.pt
Solgema/fullcalendar/browser/collectionview.pt
Solgema/fullcalendar/browser/configure.zcml
Solgema/fullcalendar/browser/content.py
Solgema/fullcalendar/browser/dx.py
Solgema/fullcalendar/browser/edit_dx_event.pt
Solgema/fullcalendar/browser/eventview.pt
Solgema/fullcalendar/browser/folderquery.pt
Solgema/fullcalendar/browser/folderview.pt
Solgema/fullcalendar/browser/icalexport.py
Solgema/fullcalendar/browser/layout.pt
Solgema/fullcalendar/browser/query.py
Solgema/fullcalendar/browser/topicquery.pt
Solgema/fullcalendar/browser/topicview.pt
Solgema/fullcalendar/browser/vars.js.pt
Solgema/fullcalendar/browser/views.py
Solgema/fullcalendar/locales/Solgema.fullcalendar.pot
Solgema/fullcalendar/locales/plone-manual.pot
Solgema/fullcalendar/locales/plone.pot
Solgema/fullcalendar/locales/update.sh
Solgema/fullcalendar/locales/de/LC_MESSAGES/Solgema.fullcalendar.po
Solgema/fullcalendar/locales/de/LC_MESSAGES/plone.po
Solgema/fullcalendar/locales/en/LC_MESSAGES/Solgema.fullcalendar.po
Solgema/fullcalendar/locales/en/LC_MESSAGES/plone.po
Solgema/fullcalendar/locales/fr/LC_MESSAGES/Solgema.fullcalendar.po
Solgema/fullcalendar/locales/fr/LC_MESSAGES/plone.po
