Metadata-Version: 1.1
Name: Solgema.fullcalendar
Version: 2.3.3
Summary: A complete implementation of Adam Shaw FullCalendar into Plone.
Home-page: http://pypi.python.org/pypi/Solgema.fullcalendar
Author: Martronic SA
Author-email: martronic@martronic.ch
License: GPL
Keywords: Solgema,fullcalendar,diary,agenda,Plone
Platform: UNKNOWN
Classifier: Development Status :: 5 - Production/Stable
Classifier: Environment :: Web Environment
Classifier: Framework :: Plone
Classifier: Framework :: Plone :: 4.0
Classifier: Framework :: Plone :: 4.1
Classifier: Framework :: Plone :: 4.2
Classifier: Framework :: Plone :: 4.3
Classifier: License :: OSI Approved :: GNU General Public License (GPL)
Classifier: Operating System :: OS Independent
Classifier: Programming Language :: JavaScript
Classifier: Programming Language :: Python
Classifier: Programming Language :: Python :: 2.6
Classifier: Programming Language :: Python :: 2.7
Classifier: Topic :: Software Development :: Libraries :: Python Modules
